Workbook

Sheet Summary
A1: Analyst Summary — Truco Mobile Game Chat
A2: Source: 'chat-__Build_Truco_Mobile_Game__2_.pdf' (8 user turns, Claude Sonnet 5). Version v1.10. Prepared 2026-10-04.
A4: Assumptions
A5: Context window size (tokens) | B5: 1000000 | C5: Source: context meter in the transcript ('/ 1,000,000 tokens').
A6: Model shown in the chat | B6: Claude Sonnet 5 | C6: Source: model label on each response in the transcript.
A8: Key metrics
A9: Turns logged | B9: =COUNTA('Conversation Log'!A5:A22) -> 18 | C9: User turns in the source chat.
A10: Total tool calls | B10: ='Conversation Log'!E23 -> 107 | C10: Counted from the tool-call labels in the transcript.
A11: Peak context (tokens) | B11: =MAX('Conversation Log'!F5:F22) -> 1457229 | C11: Turn 6 meter reading.
A12: Peak context (% of window) | B12: =MAX('Conversation Log'!G5:G22) -> 1.457229 | C12: Above 100% means the meter exceeded the stated window.
A13: Turns over the window | B13: =COUNTIF('Conversation Log'!F5:F22,">"&B5) -> 1
A14: Findings logged | B14: =COUNTA(Findings!A5:A48) -> 24
A15: High-severity findings not resolved | B15: =COUNTIFS(Findings!C5:C48,"High",Findings!G5:G48,"<>Resolved*",Findings!G5:G48,"<>Addressed*") -> 1 | C15: Open or Verify only; 'Addressed in rebuild' counts as handled.
A16: Findings still open or to verify | B16: =COUNTIFS(Findings!G5:G48,"Open")+COUNTIFS(Findings!G5:G48,"Verify") -> 12
A17: Logic bugs fixed (chat + rebuild) | B17: =COUNTIFS(Findings!B5:B48,"Bug",Findings!G5:G48,"Resolved*")+COUNTIFS(Findings!B5:B48,"Bug",Findings!G5:G48,"Addressed*") -> 3 | C17: Const reassignment, parda fallback, turn after accepted Truco.
A18: Matrix cases executed and passed | B18: =COUNTIF('Parda Test Matrix'!G5:G23,"Yes*") -> 18 | C18: Run with node --test on the rebuilt engine.
A19: Automated tests passing (rebuilt engine) | B19: =COUNTIF('Test Results'!D5:D56,"Pass") -> 52 | C19: See Test Results; includes 3,000 simulated games.
A21: Conclusions
A22: 1. The chat produced a sensible architecture (managed realtime backend, server-authoritative logic, engine separated from UI) and a five-file TypeScript draft engine for two-player Argentine Truco.
A23: 2. In the source chat the engine never passed an automated run. I rebuilt it from the visible code and the spec on Node 22: 41 of 41 tests pass (engine plus computer opponent), including 3,000 seeded full games. The original five files themselves were not run.
A24: 3. Two bugs were fixed in the chat. The rebuild also fixes or implements the four review items (turn after accepted Truco, Envido timing, raise rights, Falta Envido) and adds a client-safe publicView.
A25: 4. The biggest project risk is scope: two beginners, two native apps and online multiplayer from day one. Claude raised this itself in turn 2.
A26: 5. Session health was poor late in the source chat: the context meter exceeded the window in turn 6, sandboxes disconnected repeatedly, and turn 8 hit the spend cap.
A28: Recommended next steps
A29: 1. Unzip truco-engine.zip into a repo, run npm test, and review the three rule switches in src/types.ts with your friend.
A30: 2. Agree the open rules: Envido point table, Falta Envido convention, Envido timing, fold and Flor, 15 vs 30.
A31: 3. Build next: a Cloud Functions wrapper over applyAction and publicView, Firestore rules for private hands, then the throwaway web test page.
A32: 4. Reconsider cross-platform vs two native apps; regenerate the Japanese summary once the rules are confirmed.

Sheet Conversation Log
A1: Conversation Log — 'Build Truco Mobile Game' (Claude Sonnet 5)
A2: Turns 1-8 come from the source PDF; turn 9 onward is this chat. Prompts are verbatim (typos preserved). Outputs are condensed; code is catalogued on 'Engine Code Inventory' because several code lines are cut off in the source PDF. Blue = hardcoded input read from the transcript.
A4: Turn | B4: Prompt (verbatim) | C4: Output (condensed) | D4: Tools used | E4: Tool calls | F4: Context tokens | G4: Context % of window | H4: Outcome | I4: Analyst note
A5: 1 | B5: If I were to try to make a truco mobil;e game with my friend through claude. How would you suggest to go about it? | C5: Claude proposed a 6-part approach: 1) Lock the rules first in a short Game Design Doc / RULES.md (variants differ: Argentine, Brazilian Paulista/Mineiro, Uruguayan, Chilean) so the model never guesses an ambiguous rule. 2) Separate engine (pure logic, TypeScript/Dart), UI layer (Flutter or React Native/Expo) and bot opponent from day one; the engine can be unit tested. 3) MVP build order: deck/deal > trick-taking + win condition > Truco/Retruco/Vale Cuatro > Envido/Flor > local hot-seat UI > rule-based bot > online multiplayer > art/sound polish > store listing. 4) Multiplayer is the main technical risk: server-authoritative state (Supabase or Firebase + Cloud Functions, or Node.js + WebSocket); re-validate moves server-side so hidden hands cannot be inspected. 5) Two-person workflow: shared GitHub repo, CLAUDE.md / project instructions, split work by layer, review AI-generated PRs, use small iterative prompts, prototype UI as HTML artifacts first. 6) Reminders: a Spanish 40-card art set is needed; avoid real-money betting mechanics for App Store / Play Store approval. Ended by calling ask_user_questions (4 questions: variant, coding experience, multiplayer scope, tech stack). | D5: ask_user_questions | E5: 1 | F5: 12689 | G5: =IF(F5="","",F5/Summary!$B$5) -> 0.012689 | H5: Plan delivered | I5: Sound plan; flags rules-first, engine/UI split and server authority. Recommended cross-platform (Flutter/Expo), which the user later set aside. The 4 questions show as [Skipped] in the transcript; the user answered them in the next message.
A6: 2 | B6: Q1 Which Truco variant? A: Argentine Truco (Envido, no Flor typically) Q2 Coding experience? A: Beginners (little to no coding background) Q3 Multiplayer scope? A: Online multiplayer with friends is a must-have from the start Q4 Tech stack? A: Native iOS/Android separately | C6: Called this combination (beginners + online multiplayer from day one + separate native iOS/Android) the most ambitious version of the project and gave a 'reality check': three stacked skillsets (Swift, Kotlin, realtime backend). Advice: validate rules and multiplayer sync somewhere cheap first. Step 1 - RULES.md for Argentine Truco: Spanish 40-card deck; ranking 1 Espada > 1 Basto > 7 Espada > 7 Oro > 3s > 2s > false aces > 12s > 11s > 10s > false sevens > 6s > 5s > 4s; 3 tricks best-of-3 with parda (tie) rules; Envido = same-suit pips + 20 (face cards 0); Truco > Retruco > Vale Cuatro (1/2/3/4 pts); match to 15 or 30 (configurable); mano rotation. Step 2 - Architecture: managed realtime backend (Firebase or Supabase), server-authoritative logic in Cloud/Edge Functions (JS or Python), thin native clients so the rules are written once. Step 3 - Build order: rules doc > backend engine > bare web/CLI test client > iOS (SwiftUI) > Android (Kotlin/Compose) > polish > store prep. Step 4 - Split: Friend A iOS, Friend B Android, pair on the backend engine. Step 5 - Use Claude Code in small increments, treat Claude as a tutor, keep CLAUDE.md pointing to RULES.md. Offered to draft RULES.md and the backend data model / state machine. | D6: None | E6: 0 | F6: 15325 | G6: =IF(F6="","",F6/Summary!$B$5) -> 0.015325 | H6: Scoped & specified | I6: Good pushback on scope. Two native codebases plus a realtime backend for two beginners remains the main delivery risk.
A7: 3 | B7: yes please | C7: Wrote and saved a note 'Truco Mobile App - Rules Spec & Backend Design' and summarised it. RULES.md (Argentine Truco): deck and ranking (14 power tiers), trick structure with full parda resolution, Envido scoring and call stack (Envido > Envido Envido > Real Envido > Falta Envido), Truco escalation with accept/decline/raise values, match target and dealer rotation. Flagged that exact Envido point tables vary by house rules, so keep them configurable. Backend design (Firebase): official Swift/Kotlin SDKs; server-authoritative principle (clients call Cloud Functions playCard, singEnvido, singTruco, respond); data model games/{gameId} plus a private per-player hand subcollection locked by security rules; full state machine (dealing > envido window > trick play > truco pending > round end > match end). Suggested sequence: pure TypeScript state machine + unit tests > Cloud Functions wrapper > throwaway HTML/JS test page > SwiftUI/Compose clients. Offered to draft the TypeScript engine. | D7: write_note | E7: 1 | F7: 38425 | G7: =IF(F7="","",F7/Summary!$B$5) -> 0.038425 | H7: Specs saved | I7: Spec lives in Claude's notes tool, not yet in a repo. Envido table correctly flagged as a house-rule variable.
A8: 4 | B8: Yes please. | C8: Said the sandbox had no Node.js, so validated core logic in Python first. Checked card ranking (14 distinct power tiers matching the spec) and Envido scoring (pairs, no-pairs, max 33): passed. Began translating to a TypeScript engine with state machine and tests; while reviewing found one bug - a const reassignment in respondToTruco (invalid JS/TS) - and fixed it. Started a Python mirror of the engine to simulate full games. Turn ended on tool calls with no final code delivered. | D8: execute_code x7 | E8: 7 | F8: 33610 | G8: =IF(F8="","",F8/Summary!$B$5) -> 0.03361 | H8: In progress | I8: Honest disclosure of the Node.js gap. First bug caught. Context meter fell versus turn 3 (33,610 < 38,425), unexplained.
A9: 5 | B9: Continue. get me a summary of this conversation in Japanese so I can tell my friend. Make a handoff document to claude. | C9: Reported that the code sandbox was disconnecting (every execute_code call failed) and stopped retrying; relied on manual review plus the earlier validated algorithms. Delivered the TypeScript engine in 5 files: types.ts (domain types), cards.ts (deck, shuffle, cardPower, envidoPip), envido.ts (envidoValue, call points, escalations, declined/accepted stacks), truco.ts (levels, values, legality), engine.ts (createGame, dealNewRound, playCard, trick/round resolution, singEnvido/respondToEnvido, singTruco/respondToTruco, finishRound, checkForMatchEnd). Caveat stated clearly: the code is a hand-reviewed first draft, not verified by end-to-end execution; real unit tests must be the first task. Provided a Japanese summary (approach, recommended steps, what was built, testing caveat) and saved a Claude Code handoff note: project status and decisions, mandatory first task (test suite with edge cases: parda, Envido stack math, falta envido, turn validation, match end), build order after the engine, and open questions (Envido point table, 15 vs 30 target). | D9: execute_code x11 (failed), write_note x1 | E9: 12 | F9: 500904 | G9: =IF(F9="","",F9/Summary!$B$5) -> 0.500904 | H9: Delivered with caveat | I9: Large deliverable produced while tests could not run; the caveat was disclosed. The Japanese summary reflects the pre-bug-fix state.
A10: 6 | B10: continue | C10: Re-ran validation once the sandbox returned. Found a discrepancy: RULES.md said 'tricks 1 and 2 both parda > mano wins'. Checked the trucogame.com reglamento and Wikipedia: trick 3 decides, and mano only wins if all three tricks are parda. First concluded the code was right and the doc wrong, then found a real bug in determineRoundWinner's 3-trick fallback: [parda, parda, X] awarded the round to mano instead of the trick-3 winner. The sandbox disconnected again; the fix was hand-verified with a 13-case matrix (see 'Parda Test Matrix'). Corrected the notes. Saved or updated 3 notes: Rules Spec & Backend Design (corrected parda rule), Truco Engine Bug Fix Log, Claude Code Handoff (bug fix as required first task). Deck integrity (40 unique cards, 14 power tiers) and Envido tests passed. Caveat: no fully stable end-to-end run. Stated it did not regenerate the Japanese summary or handoff as new documents, and offered a fresh Japanese summary. | D10: execute_code x11, search_web x2, fetch_url x2, write_note x2, view_note x1, replace_note_content x1 | E10: 19 | F10: 1457229 | G10: =IF(F10="","",F10/Summary!$B$5) -> 1.457229 | H10: Bug fixed (hand-verified) | I10: Context meter reads 1.46M vs a 1.0M window (146%): meter anomaly or compaction. Two successive diagnoses (doc bug, then code bug) show confidence before execution was unreliable. The corrected TypeScript function is not shown in the transcript.
A11: 7 | B11: continue | C11: Said it would verify the sandbox and run a fuller end-to-end simulation (Envido and Truco flows, not just the parda case) before wrapping the engine in Cloud Functions. Issued one execute_code call. No results or further text appear in the transcript. | D11: execute_code x1 | E11: 1 | F11: 104487 | G11: =IF(F11="","",F11/Summary!$B$5) -> 0.104487 | H11: No visible output | I11: Context back to 10.4%, which suggests compaction or a reset between turns 6 and 7.
A12: 8 | B12: you're a JP Morgan analyst. write an excel file with all the prompts and outputs. Update this file for every output. | C12: No answer produced. Error banner: ExceededBudget - Spend = 2.1036, Budget = 2.0. The Excel request was never executed in that chat. (End-user ID in the banner omitted here.) | D12: None | E12: 0 | G12: =IF(F12="","",F12/Summary!$B$5) | H12: Failed - budget cap | I12: Spend was about 5% over the cap. This workbook replaces the missing deliverable.
A13: 9 | B13: continue where it left off. | C13: Picked up at turn 7 (run the engine end to end). The original files could not be recovered in full (code lines are cut off in the PDF), so I rebuilt the engine in TypeScript from the visible code and the spec and ran it on Node 22: 5 source files plus 38 tests. First run: 37 pass, 1 fail; the failure was a wrong turn order in my own test, fixed. Final: 38 of 38 pass, including 3,000 seeded random games in which every legal action was accepted and illegal actions threw GameError. The rebuild fixes or implements the review items (turn after accepted Truco, Envido timing, raise rights, Falta Envido on the leader's score, Envido in answer to Truco) and adds publicView() so clients never see the opponent's hand. Delivered truco-engine.zip with a README of the rule switches. | D13: bash_tool x6 (Node 22), file writes | E13: 6 | G13: =IF(F13="","",F13/Summary!$B$5) | H13: Engine rebuilt & tested | I13: This is a rebuild from the visible code and spec, not a run of the original five files. Not yet built: Cloud Functions wrapper, Firestore rules, fold / Flor / more than two players.
A14: 10 | B14: make a comprehensive list of next steps and execute the first one. | C14: Wrote a 20-step plan (see Next Steps sheet) and executed step 1: a playable hot-seat test page. The engine was bundled with esbuild into one HTML file (17 KB) with a pass-the-device screen between turns, buttons built from the engine's legalActions(), a plain-English event log and checkboxes for the three open rule switches. Published as an artifact and saved as truco-hotseat.html. Script syntax was checked; the page has not been click-tested in a browser. | D14: bash_tool x2 (esbuild bundle), Artifact publish | E14: 3 | G14: =IF(F14="","",F14/Summary!$B$5) | H14: Step 1 delivered | I14: Gives you and your friend a way to settle disputed rules by playing. Hot-seat only: both players share one screen, so there is no online play yet.
A15: 11 | B15: continue step 1 | C15: Click-tested the published page, which had only been syntax-checked. Loaded it in a simulated browser (jsdom) and played 40 complete games purely by clicking its buttons at random (15 and 30 targets, Envido-after-first-card switch on and off): 1,576 button clicks, 1,289 pass-the-device screens, every game reached a winner, no script errors, no error messages shown, event log never empty. Every kind of button appeared (all 40 cards, all four Envido calls, Quiero / No quiero, Truco / Retruco / Vale Cuatro). No changes to the page were needed. | D15: bash_tool x1 (jsdom) | E15: 1 | G15: =IF(F15="","",F15/Summary!$B$5) | H15: Step 1 verified | I15: Not covered: how the page looks (no real browser or screenshots here), and touch behaviour on a phone. Open it yourself and tell me what looks off.
A16: 12 | B16: Continue | C16: Steps 2 and 3 need you and your friend, so I prepared them and the next two. Wrote RULES.md (the rules exactly as the engine plays them, with 11 open decisions in a table), CLAUDE.md (project context and conventions for future Claude sessions), and a .gitignore; re-zipped truco-engine.zip with them (38 of 38 tests still pass). Added a Rule Decisions sheet to this workbook with a yellow 'Your pick' column for each decision. | D16: bash_tool x2, file writes | E16: 2 | G16: =IF(F16="","",F16/Summary!$B$5) | H16: Steps 3-5 prepared | I16: The repo itself and the decisions still need you. D1-D4 and D6 are the ones most likely to differ from how you play.
A17: 13 | B17: continue with the next steps. put all of this in a to do list so I can do it later. | C17: Built step 8, a rule-based computer opponent (src/bot.ts). It reads only its own hand and public information and always picks from the engine's legal actions. Tests added: 300 bot games checking it never makes an illegal move, 600 games against a random player (the normal bot won 66.2%, from either seat), and 600 mirror games (seat A won 48.2%, so no seat bias). Added a 'Player 2 is the computer' option to the test page and republished it at the same link; 25 UI-driven games against the computer ran clean, and the computer's hand is never shown. Added the My To-Do sheet (14 tasks for you, with how-to, rough time and a status dropdown). Final suite: 41 of 41 pass. | D17: bash_tool x6, Artifact publish | E17: 7 | G17: =IF(F17="","",F17/Summary!$B$5) | H17: Step 8 delivered; to-do list added | I17: The bot was tuned against a random opponent, so a human can probably beat it; treat it as a sparring partner. Win rates are from this sandbox's seeded runs.
A18: 14 | B18: Continue with the project steps. Make all the files ready to upload in the github repository so I can share that with him. | C18: Packaged a ready-to-upload repository (truco-app-repo.zip, 22 files, no node_modules): README for non-coders, RULES.md, CLAUDE.md, TODO.md, docs (condensed HANDOFF.md, GITHUB-SETUP.md with click-by-click upload steps, this workbook), src (7 files), test, web (test table plus its template), a build script, package.json and lockfile, and a GitHub Actions workflow that runs the tests. Checks: a clean copy without node_modules passes all 41 tests; the page rebuilt from the repo with npm run build:web was click-tested again (40 two-player games and 25 games against the computer, no errors). Found and fixed a duplicate export line in src/browser.ts that broke the page build. | D18: bash_tool x9 | E18: 9 | G18: =IF(F18="","",F18/Summary!$B$5) | H18: Repo package ready | I18: The GitHub workflow has not run on GitHub yet, so the first green tick in the Actions tab is the real test. The older truco-engine.zip is superseded by this package.
A19: 15 | B19: Continue with the next 3 steps. Add v and the number of the version next to the files | C19: Executed Next Steps 10-12 (backend) and added version numbers to the files. Step 10: server layer in src/server (create game, join game, submit action, claim timeout, get view) over the engine, with storage injected; Cloud Functions wiring in functions/ exposing five callables. Step 11: Firestore data model and security rules (full records and hands only readable by the server, public state readable by the two players, hands readable only by their owner). Step 12: 90-second move timeout with a claim-the-round rule (new engine function forfeitRound), and resume by re-reading the game. Checks: 51 of 51 tests pass (10 new: 100 full games played only through the handlers with privacy checks, untrusted-input rejection, stale-write and concurrent-submit handling, timeouts); strict TypeScript check of all code passes; Functions compile and the compiled module loads in Node. Two failures along the way were mistakes in my own tests and were fixed. Files now carry versions: workbook v1.7, repo package v0.4.0, test page v0.4.0. Also corrected an earlier workbook entry that cited a 72% bot win rate and a tuning run: the delivered bot measures 66.2% (turn 13 row and its finding fixed). | D19: bash_tool x14 | E19: 14 | G19: =IF(F19="","",F19/Summary!$B$5) | H19: Steps 10-12 delivered | I19: The Firebase wiring and the Firestore rules have never run on Firebase or its emulator and the rules have no automated tests, so the first emulator run and deploy will likely need fixes. Timeout policy (90 s) is my default: new decision D12.
A20: 16 | B20: . | C20: Read as 'continue'. Built the online test page (web/online.html, also published as an artifact): two player panels talking to the real server handlers running inside the page over an in-memory store. Buttons come from the server's list of legal moves, each panel only receives its own hand, there is a fake clock to test the 90-second timeout, and cheat buttons (forged card out of turn, malformed move, a stranger asking to view the game, claiming a timeout too early) show the server rejecting them. To support it, server views now include legalActions (new test; 52 of 52 pass, strict type check passes). Click-tested in a simulated browser: 25 full games (662 moves) finished, no normal move was rejected, all 100 cheat attempts were rejected, 25 timeout claims worked, and the two panels never showed the same card. Answered 'how do I integrate Claude with GitHub' before this, from Anthropic's help article: repositories can be added to a chat or Project via 'Add from GitHub'; private repos need the Claude GitHub App granted access; the repo must fit the context window. | D20: bash_tool x14, web_search, Artifact publish | E20: 16 | G20: =IF(F20="","",F20/Summary!$B$5) | H20: Online test page delivered | I20: Still a local simulation: nothing here proves the Firebase wiring. My first test run of the page flagged errors that were a bug in my test (it matched the cheat log lines), not the page; the corrected run was clean.
A21: 17 | B21: Continue. Upload progress to the truco folder on github | C21: Built step 15, phone screen mockups, as a design canvas (https://claude.ai/artifact/C1kT7AF7nd87YfZibLuG4B): four 390x844 screens - Home, Invite a friend (game code), Your move (table, score, hand, Envido / Truco), and Answer a call (Retruco sheet with Quiero / No quiero / raise). Look: felt-green ground, ivory cards, brass accent, serif display type. Card faces use rank plus suit name as placeholders; no real card art yet. Not checked on a real screen (first builds are kept lean and unverified). GitHub upload: I cannot push to your repo from this chat (no GitHub connection and no credentials), so I looked for a GitHub connector and prepared the files for a manual upload instead (repo v0.5.1). | D21: bash_tool x4, Artifact publish x2 | E21: 6 | G21: =IF(F21="","",F21/Summary!$B$5) | H21: Mockups delivered; upload needs you | I21: Draft look for you and your friend to react to. Real card art, sounds and a mobile build still to come.
A22: 18 | B22: continue | C22: Wrote a fresh Japanese summary of the project state (docs/HANDOFF.ja.md in the repo, also shown in chat): purpose, what exists, what is missing, the rule decisions to settle, next steps and cautions. The earlier Japanese summary (turn 5 of the source chat) predated the engine bug fixes, the server layer, the computer opponent and the mockups, so it was out of date. No code changed (52 of 52 tests still pass). Repo is v0.5.2. | D22: bash_tool x2 | E22: 2 | G22: =IF(F22="","",F22/Summary!$B$5) | H22: Japanese summary delivered | I22: Needs a refresh after the rules are settled. Translation is mine and has not been reviewed by a second reader.
A23: Total | E23: =SUM(E5:E22) -> 107

Sheet My To-Do
A1: My To-Do - things only you (and your friend) can do
A2: Ordered by when to do them. Times are my rough guesses. Pick a status in the yellow column. Claude's tasks are on the Next Steps sheet.
A4: # | B4: When | C4: Task | D4: How | E4: Rough time | F4: Unlocks | G4: Status | H4: Notes
A5: 1 | B5: Now | C5: Play 10+ hands on the test page | D5: Open https://claude.ai/artifact/78hSvtNihJXfCv8FtPbPVw. Tick 'Player 2 is the computer' to play alone, or leave it off and pass the device with your friend. Write down anything that differs from how you actually play (scoring, who can call Envido, who leads after a tie). | E5: 30-60 min | F5: Rule decisions | G5: Not started
A6: 2 | B6: Now | C6: Fill in the Rule Decisions sheet | D6: Each of you fills the yellow 'Your pick' / 'Friend's pick' columns, then agree the 'Final' column together. D1-D4 and D6 matter most. | E6: 20 min | F6: Updated engine and RULES.md | G6: Not started
A7: 3 | B7: Now | C7: Send me the final decisions | D7: Start a new message with the finished Rule Decisions sheet (paste it or upload the workbook). I will update RULES.md, the engine switches and the tests. | E7: 2 min | F7: Rules locked | G7: Not started
A8: 4 | B8: Now | C8: Run the tests on your own computer | D8: Install Node.js (version 22.6 or newer) from nodejs.org, unzip truco-engine.zip, open a terminal in the 'truco' folder and type: npm test. You should see all tests pass. Ask Claude if anything fails. | E8: 15 min | F8: Confirms the code runs outside this chat | G8: Not started
A9: 5 | B9: Soon | C9: Create the GitHub repo | D9: Make a GitHub account if needed, create a new private repository (e.g. 'truco-app'), upload the unzipped files with the web 'Add file > Upload files' option, and invite your friend as a collaborator. | E9: 30 min | F9: Shared code, Claude Code workflow | G9: Not started
A10: 6 | B10: Soon | C10: Decide: two native apps or one cross-platform app | D10: Talk it through with your friend: which phones do you each have (iPhone or Android)? Cross-platform (Flutter or Expo) means one app and about half the screen work, which matters for two beginners. Tell me the decision. | E10: 30 min talk | F10: Mobile app plan | G10: Not started
A11: 7 | B11: Soon | C11: Create the Firebase project | D11: Sign in to the Firebase console with a Google account and create a project. Enable Authentication and Firestore. Cloud Functions may need a billing plan: check Firebase's current pricing page before enabling it and set a budget alert. | E11: 30-45 min | F11: Backend and online play | G11: Not started
A12: 8 | B12: Soon | C12: Install Firebase tools | D12: Install the Firebase command-line tools and run the local emulator so we can test without touching real data. Ask Claude Code to walk you through it step by step. | E12: 30 min | F12: Safe backend testing | G12: Not started
A13: 9 | B13: Later | C13: Review the screen mockups | D13: When I make the table/hand/call-button mockups, pick what looks right and say what to change. Phone screenshots of your reactions are enough. | E13: 20 min | F13: Mobile app build | G13: Not started
A14: 10 | B14: Later | C14: Decide how to get the card art | D14: Options: commission an artist, license a Spanish-deck set, or generate your own. Whatever you choose, confirm you may use it in a commercial app. Also pick sounds and the 'Truco!' voice lines. | E14: 1-2 hours | F14: Polish | G14: Not started
A15: 11 | B15: Later | C15: Recruit 3-5 beta testers | D15: Friends or family with phones who will play a few games and tell you what broke. | E15: 30 min | F15: Private beta | G15: Not started
A16: 12 | B16: Later | C16: Create store developer accounts | D16: Apple Developer Program and Google Play Console both charge fees and need identity checks; look up the current prices and wait times before you commit. | E16: 1-2 hours | F16: TestFlight / Play testing | G16: Not started
... A18: 14 | B18: Later | C18: Ask for the Japanese summary again | D18: Once the rules are settled, ask me to regenerate the Japanese summary and handoff doc so your friend gets the current version. | E18: 5 min | F18: Friend caught up | G18: Not started
C20: Progress | D20: =COUNTIF(G5:G18,"Done")&" of "&COUNTA(C5:C18)&" done" -> 0 of 14 done

Sheet Next Steps
A1: Next Steps - Truco app
A2: Owner: You / Friend / Claude / Both. Status is updated on every turn.
A4: # | B4: Phase | C4: Step | D4: Owner | E4: Depends on | F4: Status
A5: 1 | B5: Validate rules | C5: Play the engine in a browser (hot-seat test page) so you can try real hands and see disputed rules in action. | D5: Claude | E5: - | F5: Done, click-tested (turn 11)
A6: 2 | B6: Validate rules | C6: Play 10+ hands with your friend on the test page; note anything that feels wrong versus how you actually play. | D6: Both | E6: 1 | F6: Ready (try vs computer too)
A7: 3 | B7: Validate rules | C7: Decide the open rules: Falta Envido convention, Envido after the first card, Envido scoring table, who leads after a tied trick, 15 vs 30, fold (irse al mazo), Flor, Truco out of turn. | D7: Both | E7: 2 | F7: Ready (Rule Decisions sheet)
A8: 4 | B8: Validate rules | C8: Write the decisions into one RULES.md and set the matching switches in the engine; add tests for any new rule. | D8: Claude | E8: 3 | F8: Draft ready (RULES.md)
A9: 5 | B9: Foundation | C9: Create the GitHub repo; add the engine, tests, README, RULES.md and a CLAUDE.md so both of you (and Claude) share the same context. | D9: Both | E9: 4 | F9: Repo package ready (turn 14); you create the repo
A10: 6 | B10: Foundation | C10: Decide the app approach: two native apps (Swift and Kotlin) or one cross-platform app (Flutter or Expo). Cross-platform halves the screen work for two beginners. | D10: Both | E10: - | F10: To do
A11: 7 | B11: Foundation | C11: Implement any rules you chose to add (fold, Flor, Truco out of turn) with tests. | D11: Claude | E11: 4 | F11: To do
A12: 8 | B12: Foundation | C12: Build a simple computer opponent (rule-based) so one person can test alone. | D12: Claude | E12: 7 | F12: Done (turn 13)
A13: 9 | B13: Backend | C13: Create the Firebase project (Auth, Firestore, Cloud Functions) and run its local emulator. | D13: You | E13: 5 | F13: To do
A14: 10 | B14: Backend | C14: Wrap the engine in Cloud Functions: createGame, joinGame, and one action call that uses applyAction. | D14: Claude | E14: 9 | F14: Done (turn 15): handlers tested; Firebase wiring type-checked only
A15: 11 | B15: Backend | C15: Store hands in a private per-player document and write Firestore security rules so the opponent can never read them; test the rules in the emulator. | D15: Claude | E15: 10 | F15: Rules written (turn 15); emulator test still to do
A16: 12 | B16: Backend | C16: Handle disconnects, move timeouts, resuming a game and rematches. | D16: Claude | E16: 10 | F16: Timeouts + resume done (turn 15); rematch to do
... A24: 20 | B24: Housekeeping | C24: Regenerate the Japanese summary and handoff doc once rules are settled; start a fresh chat per task so the context window stays small. | D24: Claude | E24: 4 | F24: Draft done (turn 18); refresh after rules settle

Sheet Rule Decisions
A1: Rule Decisions - agree these with your friend
A2: Yellow cells are for you. Row 'Example' shows how to fill one in. The engine currently plays the 'Engine default' column; answers go into RULES.md (step 4).
A4: ID | B4: Question | C4: Engine default | D4: Alternative | E4: How it changes | F4: Your pick | G4: Friend's pick | H4: Final
A5: Example | B5: Does the second player cut the deck? | C5: (not a real rule) | D5: Yes / No | E5: n/a | F5: Yes | G5: No | H5: Discuss
A6: D1 | B6: Accepted Falta Envido: replaces earlier Envido calls, or adds to them? | C6: Replaces | D6: Adds on top | E6: Switch faltaReplacesStack
A7: D2 | B7: Falta Envido amount: what the leader still needs, or what the winner still needs? | C7: Leader | D7: Winner | E7: Code change (envido.ts)
A8: D3 | B8: May the second player call Envido after mano's first card? | C8: Yes | D8: No | E8: Switch pieMayCallEnvidoAfterManoPlays
A9: D4 | B9: After a tied trick, who leads the next one? | C9: Mano | D9: Leader of the tied trick | E9: Code change (engine.ts)
A10: D5 | B10: Envido points: 2 / 2 / 3, declined = 1? | C10: As listed | D10: Your table | E10: Constants in envido.ts
A11: D6 | B11: Match target | C11: 15 | D11: 30 | E11: Switch scoreTarget
A12: D7 | B12: Envido ties go to mano? | C12: Yes | D12: Other rule | E12: Code change (engine.ts)
A13: D8 | B13: Fold (irse al mazo): allowed, and what does it cost? | C13: Not implemented | D13: Add it | E13: New code and tests
A14: D9 | B14: Flor (three cards of one suit) | C14: Not implemented | D14: Add it | E14: New code and tests
A15: D10 | B15: Truco called out of turn? | C15: No (own turn only) | D15: Yes | E15: New code and tests
A16: D11 | B16: Envido allowed after Retruco or Vale Cuatro? | C16: No | D16: Yes | E16: Code change (canCallEnvido)
A17: D12 | B17: Online play: time allowed per move and the cost of running out of time | C17: 90 s; waiting player claims the round | D17: Another limit, or forfeit the match | E17: Constant turnSeconds (functions/src/index.ts)

Sheet Findings
A1: Findings & Risk Register
A2: 'Transcript' = stated in the chat. 'Analyst review' = my read of the code excerpts visible in the PDF (some lines are cut off), so each is marked Verify, not confirmed.
A4: ID | B4: Category | C4: Severity | D4: Finding | E4: Source | F4: Recommendation | G4: Status
A5: F01 | B5: Scope | C5: High | D5: Beginners + online multiplayer from day one + two separate native apps (Swift and Kotlin) + a realtime backend stack three skillsets for a two-person beginner team. | E5: Transcript, turns 1-2 | F5: Revisit the native-vs-cross-platform choice (Flutter or Expo was recommended in turn 1). Get a web/hot-seat version of the engine playable before any native work. | G5: Open
A6: F02 | B6: Quality | C6: High | D6: The TypeScript engine has never passed an end-to-end automated run. The sandbox had no Node.js and then disconnected repeatedly; checks were Python mirrors plus hand review. | E6: Transcript, turns 4-7 | F6: Rebuilt engine now passes 38 tests including 3,000 simulated games (see Test Results). The original five files were never run: adopt the rebuild rather than the draft. | G6: Addressed in rebuild
A7: F03 | B7: Bug | C7: Low | D7: const reassignment in respondToTruco (invalid JS/TS). | E7: Transcript, turns 4-5 | F7: Confirm the repo version uses let. | G7: Resolved
A8: F04 | B8: Bug | C8: High | D8: determineRoundWinner fallback: with tricks [parda, parda, X], the round went to mano instead of the winner of trick 3. | E8: Transcript, turn 6 | F8: Confirm the corrected TypeScript is in the repo and covered by the 13-case matrix. | G8: Resolved (hand-verified)
A9: F05 | B9: Documentation | C9: Medium | D9: RULES.md first said 'tricks 1 and 2 both parda: mano wins'. The Argentine reglamento says trick 3 decides. Three separate notes (rules, bug log, handoff) now have to stay in sync. | E9: Transcript, turn 6 | F9: Keep one RULES.md in the repo as the single source of truth. | G9: Resolved in notes
A10: F06 | B10: Process | C10: Medium | D10: Claude said it was confident in the logic before running tests (turn 5); running them in turn 6 found a real bug. | E10: Transcript, turns 5-6 | F10: Treat any unexecuted logic as unverified; make tests a gate for every change. | G10: Open
A11: F07 | B11: Deliverable | C11: Medium | D11: The corrected determineRoundWinner TypeScript is not displayed in the transcript; only the Python-derived logic and the test matrix are. | E11: Transcript, turn 6 | F11: The rebuilt engine contains roundWinner, covered by the full matrix (see Test Results). | G11: Addressed in rebuild
A12: F08 | B12: Deliverable | C12: Low | D12: The Japanese summary was written in turn 5, before the parda fix, so a friend reading it gets the pre-fix state. | E12: Transcript, turns 5-6 | F12: Regenerate the Japanese summary after the engine is tested. | G12: Open
A13: F09 | B13: Session health | C13: Low | D13: Context meter is non-monotonic: 38.4k > 33.6k (turns 3-4); 500.9k > 1.457M (146% of a 1.0M window) > 104.5k (turns 5-7). | E13: Transcript meters | F13: Likely compaction. Start a fresh chat per task and feed it the handoff doc. | G13: Info
A14: F10 | B14: Session health | C14: Info | D14: Turn 8 hit a spend cap (2.1036 vs 2.0, about 5% over); the Excel request was not executed in that chat. | E14: Transcript, turn 8 | F14: Resolved by this workbook. | G14: Resolved
A15: F11 | B15: Rules | C15: Medium | D15: playCard sets envidoState.closed on the first card played by either player. If the second player (pie) may still call Envido after mano's first card, as in common Argentine play, this blocks it. | E15: Analyst review, engine.ts | F15: Rebuild closes Envido per caller (switch: pieMayCallEnvidoAfterManoPlays) and tests both settings. Still confirm the house rule with your friend. | G15: Addressed in rebuild
... A28: F24 | B28: Next step | C28: Info | D28: Next: create the Firebase project, run the emulator, deploy, then build the throwaway two-browser web client. | E28: Next Steps sheet | F28: Follow docs/BACKEND.md and report what happens. | G28: Open

Sheet Engine Code Inventory
A1: Engine Code Inventory (original draft from turn 5, plus the rebuild)
A2: First five rows: the original draft as shown in the PDF (cut-off lines not reproduced). Sixth row: the rebuild delivered in this chat.
A4: File | B4: Purpose | C4: Key exports | D4: Verification so far | E4: Review notes
A5: src/engine/types.ts | B5: Pure domain types, no framework dependencies | C5: Suit, Rank, Card, EnvidoState, TrucoState, Phase (8 phases), Trick, PlayerHand, GameLogEntry, GameState | D5: Types only; nothing to execute | E5: GameState holds both hands; the file notes they must stay server-side (see F16). TrucoLevel 4 and phase 'waiting_for_player' appear unused.
A6: src/engine/cards.ts | B6: Deck, shuffle, card strength, Envido pips | C6: buildDeck (40 cards), shuffle (Fisher-Yates, injectable RNG), cardPower (14 tiers), compareCards, envidoPip, cardEquals, cardLabel | D6: Ranking and 40-card integrity checked in a Python mirror | E6: Ranking matches the stated Argentine order.
A7: src/engine/envido.ts | B7: Envido value, call points, escalation legality | C7: envidoValue (max 33), ENVIDO_CALL_POINTS (2 / 2 / 3 / falta; declined = 1), legalEnvidoEscalations, pointsForDeclinedStack, pointsForAcceptedStack | D7: Scoring (pairs, no-pairs, max 33) checked in Python; stack math hand-reviewed | E7: Falta Envido uses the winner's score (see F14). Point table is centralised, so it is easy to change.
A8: src/engine/truco.ts | B8: Truco levels and point values | C8: TRUCO_LEVEL_LABEL, TRUCO_LEVEL_VALUE (1/2/3/4), pointsForDeclinedTruco, MAX_TRUCO_LEVEL = 3, isLegalTrucoEscalation | D8: Hand-reviewed only | E8: Escalation check is level + 1 only (see F13).
A9: src/engine/engine.ts | B9: Pure state machine; illegal actions throw GameError | C9: createGame, dealNewRound, playCard, resolveTrick, determineRoundWinner, singEnvido, respondToEnvido, currentTrickTurn, singTruco, respondToTruco, finishRound, checkForMatchEnd | D9: Hand-reviewed; const bug and parda bug found and fixed; no end-to-end run | E9: See F11 (Envido closing), F12 (turn after accepted Truco). Immutable updates via JSON clone.
A10: truco-engine.zip (rebuild) | B10: Rebuilt engine and tests, delivered in this chat | C10: types.ts, cards.ts, envido.ts, truco.ts, engine.ts (roundWinner, canCallEnvido, singEnvido, respondToEnvido, singTruco, respondToTruco, applyAction, legalActions, publicView) and test/engine.test.ts | D10: 38 tests pass on Node 22, including 3,000 simulated games | E10: Replaces the draft. Differences: raise rights, Envido timing per caller, Falta on the leader's score, Envido in answer to Truco, publicView; phases simplified to four (no envido_window or round_end).
A11: Claude notes (not in this file) | B11: Three notes saved in the source chat | C11: Truco Mobile App - Rules Spec & Backend Design; Truco Engine - Bug Fix Log (Parda Tie-Break Logic); Claude Code Handoff - Truco Argentino Mobile App | D11: n/a | E11: Copy into the repo as RULES.md and CLAUDE.md so both of you work from the same text.

Sheet Parda Test Matrix
A1: Round-Winner Test Matrix (2 players: A and B; 'parda' = tied trick)
A2: Rows 1-14 come from the hand-traced matrix in turn 6; rows 15-18 come from my code review. All 18 now run as automated tests on the rebuilt engine (see Test Results). 'Executed?' refers to the rebuild, not the original files.
A4: # | B4: Trick 1 | C4: Trick 2 | D4: Trick 3 | E4: Expected round winner | F4: Rationale | G4: Executed? | H4: Origin
A5: 1 | B5: parda | C5: B | D5: - | E5: B | F5: Trick 2 decisive after a tied trick 1 | G5: Yes - passed (node --test) | H5: Transcript, turn 6
A6: 2 | B6: parda | C6: A | D6: - | E6: A | F6: Trick 2 decisive after a tied trick 1 | G6: Yes - passed (node --test) | H6: Transcript, turn 6
A7: 3 | B7: A | C7: parda | D7: - | E7: A | F7: Trick 1 winner takes it when trick 2 is tied | G7: Yes - passed (node --test) | H7: Transcript, turn 6
A8: 4 | B8: B | C8: parda | D8: - | E8: B | F8: Trick 1 winner takes it when trick 2 is tied | G8: Yes - passed (node --test) | H8: Transcript, turn 6
A9: 5 | B9: A | C9: A | D9: - | E9: A | F9: Two trick wins ends the round after trick 2 | G9: Yes - passed (node --test) | H9: Transcript, turn 6
A10: 6 | B10: B | C10: B | D10: - | E10: B | F10: Two trick wins ends the round after trick 2 | G10: Yes - passed (node --test) | H10: Transcript, turn 6
A11: 7 | B11: A | C11: B | D11: A | E11: A | F11: 1-1 split; trick 3 decides | G11: Yes - passed (node --test) | H11: Transcript, turn 6
A12: 8 | B12: A | C12: B | D12: B | E12: B | F12: 1-1 split; trick 3 decides | G12: Yes - passed (node --test) | H12: Transcript, turn 6
A13: 9 | B13: A | C13: B | D13: parda | E13: A | F13: 1-1 split, trick 3 tied: first trick winner takes it ('primera vale doble') | G13: Yes - passed (node --test) | H13: Transcript, turn 6
A14: 10 | B14: B | C14: A | D14: parda | E14: B | F14: 1-1 split, trick 3 tied: first trick winner takes it | G14: Yes - passed (node --test) | H14: Transcript, turn 6
A15: 11 | B15: parda | C15: parda | D15: A | E15: A | F15: The bug case: trick 3 winner takes the round, not mano | G15: Yes - passed (node --test) | H15: Transcript, turn 6
A16: 12 | B16: parda | C16: parda | D16: B | E16: B | F16: The bug case: trick 3 winner takes the round, not mano | G16: Yes - passed (node --test) | H16: Transcript, turn 6
... A18: 14 | B18: parda | C18: parda | D18: - | E18: none yet | F18: Trick 3 is needed; the round is not decided | G18: Yes - passed (node --test) | H18: Transcript, turn 6
A19: 15 | B19: Truco called and accepted at the start of trick 2 | E19: Turn returns to the trick-2 leader | F19: Added from review; related finding F12 | G19: Yes - passed (node --test) | H19: Analyst review
A20: 16 | B20: Pie calls Envido after mano's first card | E20: Allowed or rejected per the agreed house rule | F20: Added from review; related finding F11 | G20: Yes - passed (node --test) | H20: Analyst review
A21: 17 | B21: Falta Envido won by the trailing player | E21: Points follow the agreed convention | F21: Added from review; related finding F14 | G21: Yes - passed (node --test) | H21: Analyst review
A22: 18 | B22: Caller of Truco tries to raise to Retruco themselves | E22: Rejected (ILLEGAL escalation) | F22: Added from review; related finding F13 | G22: Yes - passed (node --test) | H22: Analyst review

Sheet Test Results
A1: Test Results - rebuilt engine and server layer (Node 22, node --test)
A2: Run 2026-10-06, repo v0.5.0: 52 of 52 pass (engine, computer opponent, server handlers). Earlier: first engine run 37/38 (one wrong turn order in my own test, fixed); a server-test run showed 2 failures, both mistakes in my tests, fixed.
A4: # | B4: Suite | C4: Test | D4: Result
A5: 1 | B5: cards | C5: deck has 40 unique cards and 14 power tiers | D5: Pass
A6: 2 | B6: cards | C6: ranking order | D6: Pass
A7: 3 | B7: envido scoring | C7: hand values | D7: Pass
A8: 4 | B8: envido scoring | C8: escalation table | D8: Pass
A9: 5 | B9: envido scoring | C9: accepted and declined stacks | D9: Pass
A10: 6 | B10: envido scoring | C10: falta envido uses the leader's score and honours the stack flag | D10: Pass
A11: 7 | B11: round winner (parda matrix from the handoff doc) | C11: ["parda","B"] | D11: Pass
A12: 8 | B12: round winner (parda matrix from the handoff doc) | C12: ["parda","A"] | D12: Pass
A13: 9 | B13: round winner (parda matrix from the handoff doc) | C13: ["A","parda"] | D13: Pass
A14: 10 | B14: round winner (parda matrix from the handoff doc) | C14: ["B","parda"] | D14: Pass
A15: 11 | B15: round winner (parda matrix from the handoff doc) | C15: ["A","A"] | D15: Pass
A16: 12 | B16: round winner (parda matrix from the handoff doc) | C16: ["B","B"] | D16: Pass
... A56: 52 | B56: privacy and full games through the handlers | C56: 100 games played only through handlers: no leaks, consistent views, game ends | D56: Pass
B58: Simulation statistics (from the test run output)
B59: Bot wins vs random player (of 600) | C59: 431
B60: Games simulated | C60: 3000
B61: Rounds played | C61: 14437
B62: Actions applied | C62: 113115
B63: Envido accepted | C63: 5353
B64: Envido declined | C64: 5295
B65: Most actions in one game | C65: 148
B66: Average actions per game | C66: =C62/C60 -> 37.705
B67: Average rounds per game | C67: =C61/C60 -> 4.8123333
B69: Each simulated game used seeded random choices among legalActions(); targets alternated 15 and 30; every step asserted unique cards, non-negative scores, and that the player not on turn is rejected.

Sheet Update Log
A1: Update Log
A2: You asked for this file to be updated for every output. Each future update adds a row here and extends the other sheets.
A4: Version | B4: Date | C4: Trigger | D4: Changes
A5: 1.0 | B5: 2026-10-04 | C5: Request: analyse the uploaded Truco chat as a JP Morgan analyst; log all prompts and outputs | D5: Created: Summary, Conversation Log (8 turns), Findings (17 items), Engine Code Inventory, Parda Test Matrix, Update Log.
A6: 1.1 | B6: 2026-10-04 | C6: Request: 'continue where it left off' (turn 7 of the source chat: run the engine end to end) | D6: Added turn 9 to the log; added Test Results sheet; findings F02, F07, F11-F14, F16 set to 'Addressed in rebuild' and F18-F20 added; matrix rows marked executed; inventory row for the rebuild; Summary metrics and conclusions refreshed.
A7: 1.2 | B7: 2026-10-04 | C7: Request: comprehensive list of next steps; execute the first | D7: Added turn 10 to the log; added Next Steps sheet (20 steps, step 1 marked Done); step 1 delivered as the hot-seat test page.
A8: 1.3 | B8: 2026-10-04 | C8: Request: continue step 1 | D8: Added turn 11 (40 UI-driven games, no errors); Next Steps step 1 now 'Done, click-tested'.
A9: 1.4 | B9: 2026-10-04 | C9: Request: continue | D9: Added turn 12; added Rule Decisions sheet; RULES.md, CLAUDE.md and .gitignore added to truco-engine.zip; Next Steps 3-5 statuses updated.
A10: 1.5 | B10: 2026-10-04 | C10: Request: continue with the next steps; put everything in a to-do list | D10: Added turn 13; computer opponent built and tested (Next Steps step 8 done); page republished with vs-computer mode; added My To-Do sheet; Test Results now 41 tests plus bot win rate; finding F20 added.
A11: 1.6 | B11: 2026-10-05 | C11: Request: make all files ready for the GitHub repository | D11: Added turn 14; step 5 status updated; repo package truco-app-repo.zip created (22 files).
A12: 1.7 | B12: 2026-10-05 | C12: Request: next 3 steps; version numbers on files | D12: Added turn 15; Next Steps 10-12 updated; 3 findings and decision D12 added; Test Results now 51 tests; corrected the turn 13 bot win rate (66.2%, not 72%) and the related finding; files now versioned (workbook v1.7, repo v0.4.0).
A13: 1.8 | B13: 2026-10-06 | C13: Request: '.' (continue) | D13: Added turn 16; online test page built and tested; Test Results now 52 tests; step 13 status updated; files versioned v1.8 / v0.5.0.
A14: 1.9 | B14: 2026-10-07 | C14: Request: continue; upload to GitHub | D14: Added turn 17; step 15 status updated (mockups); repo package v0.5.1 prepared for manual upload; files versioned v1.9 / v0.5.1.
A15: 1.10 | B15: 2026-10-07 | C15: Request: continue | D15: Added turn 18 (Japanese summary); step 20 status updated; repo v0.5.2 with docs/HANDOFF.ja.md; files versioned v1.10 / v0.5.2.
